pylocalsmtp/__init__.py
pylocalsmtp/app.py
pylocalsmtp/cmd.py
pylocalsmtp/handlers.py
pylocalsmtp/helpers.py
pylocalsmtp/models.py
pylocalsmtp/settings.py
pylocalsmtp/smtp.py
pylocalsmtp/medias/css/.DS_Store
pylocalsmtp/medias/css/email.css
pylocalsmtp/medias/css/pure-min.css
pylocalsmtp/medias/js/.DS_Store
pylocalsmtp/medias/js/angular-sanitize.min.js
pylocalsmtp/medias/js/angular-sanitize.min.js.map
pylocalsmtp/medias/js/angular.min.js
pylocalsmtp/medias/js/angular.min.js.map
pylocalsmtp/medias/js/app.js
pylocalsmtp/medias/js/sockjs-0.3.min.js
pylocalsmtp/medias/js/controllers/app-controllers.js
pylocalsmtp/medias/js/filters/app-filters.js
pylocalsmtp/medias/js/filters/igTruncate.js
pylocalsmtp/templates/.DS_Store
pylocalsmtp/templates/index.html
pylocalsmtp/utils/__init__.py
pylocalsmtp/utils/http.py
pylocalsmtp/utils/six.py
pylocalsmtp/utils/termcolors.py
pylocalsmtp-1.0.0.data/data/pylocalsmtp/LICENSE
pylocalsmtp-1.0.0.data/data/pylocalsmtp/README.md
pylocalsmtp-1.0.0.dist-info/DESCRIPTION.rst
pylocalsmtp-1.0.0.dist-info/entry_points.txt
pylocalsmtp-1.0.0.dist-info/METADATA
pylocalsmtp-1.0.0.dist-info/metadata.json
pylocalsmtp-1.0.0.dist-info/RECORD
pylocalsmtp-1.0.0.dist-info/top_level.txt
pylocalsmtp-1.0.0.dist-info/WHEEL
