Metadata-Version: 2.0
Name: pylocalsmtp
Version: 1.0.0
Summary: Ouvre un mini serveur SMTP en local avec inbox dans une interface web.
Home-page: https://bitbucket.org/m_clement/pylocalsmtp/
Author: Martyn CLEMENT
Author-email: martyn.clement@gmail.com
License: MIT
Platform: UNKNOWN
Classifier: Development Status :: 4 - Beta
Classifier: Environment :: Web Environment
Classifier: Intended Audience :: Developers
Classifier: Natural Language :: French
Classifier: License :: OSI Approved :: MIT License
Classifier: Operating System :: OS Independent
Classifier: Programming Language :: Python
Classifier: Programming Language :: Python :: 2
Classifier: Programming Language :: Python :: 2.6
Classifier: Programming Language :: Python :: 2.7
Classifier: Topic :: Software Development :: Libraries :: Python Modules
Requires-Dist: peewee (==2.2.2)
Requires-Dist: tornado (==3.2)
Requires-Dist: wsgiref (==0.1.2)
Requires-Dist: sockjs-tornado (==1.0.0)
